[
  {
    "type": 0,
    "content": "The library's tall glass doors reflected Auri's outline: crimson skin flushed from the walk over, dark hair in a tight braid. Polished enough to look intentional. First impressions mattered. People needed to see a competent tutor, not a scholarship kid clawing her way up through borrowed books and sleepless nights. \n\nThe scent of old parchment and binding glue stirred something warm in her chest. It smelled like home. Her mentor Artorius covered every surface of his tower with textbooks, the air holding candle smoke and powdery pages. Here, the prestige felt sharper, but the smell was the same. \n\nShe stepped inside, tail wrapped neatly around her leg. *Professional*, she reminded herself. *Composed*. \n\nSunlight filtered through the tall windows, casting pale gold stripes across the tables. Dust motes drifted lazily, catching light like tiny stars. \n\nShe spotted Sol at the table before he noticed her approaching. Even from across the room, she could sense his magic, unbidden and effortless, reacting to his presence the way sparks hovered near an open flame. \n\nAuri crossed the room in careful strides, her boots barely making a sound. She set her books down softly and offered Sol a polite nod. \n\nShe sat, smoothing her pants and then her notes: ecto-flow charts, resonance tables, color-coded in the margins. She was organized and prepared. \n\n\"Today we're covering foundational magic theory,\" she said matter-of-factly. \"Stable illusions require structure, not just instinct and scenic displays.\"\n\nHer words were both an insult and a compliment. Sol's magic was undeniably impressive. \n\nAs she lifted her gaze, her criticism was clear, but so was her admiration. \n\n\"When you're ready,\" she said evenly, controlled, \"start with the basics: the origin of all magical energy. If you know that, we can build from there.\"\n\nShe folded her hands, back straight. *Professional. Composed.*\n<@155436835013656576>",
    "mentions": [
      {
        "id": "155436835013656576",
        "username": "pyroshadow",
        "avatar": "ed853f9f1777de28c22f287e735ce2b1",
        "discriminator": "0",
        "public_flags": 64,
        "flags": 64,
        "banner": null,
        "accent_color": null,
        "global_name": "Nightingale",
        "avatar_decoration_data": {
          "asset": "a_670b722e56740d11d1e6fe55b8094013",
          "sku_id": "1343751617303805983",
          "expires_at": null
        },
        "collectibles": {
          "nameplate": {
            "sku_id": "1377377712028516443",
            "asset": "nameplates/nameplates_v2/spirit_moon/",
            "label": "COLLECTIBLES_NAMEPLATES_V2_SPIRIT_MOON_A11Y",
            "palette": "violet"
          }
        },
        "display_name_styles": {
          "font_id": 8,
          "effect_id": 2,
          "colors": [
            3163762,
            9709528
          ]
        },
        "banner_color": null,
        "clan": {
          "identity_guild_id": "394252141138804736",
          "identity_enabled": true,
          "tag": "RVYN",
          "badge": "6082c2553b03b47ccaea5203567df3cf"
        },
        "primary_guild": {
          "identity_guild_id": "394252141138804736",
          "identity_enabled": true,
          "tag": "RVYN",
          "badge": "6082c2553b03b47ccaea5203567df3cf"
        }
      }
    ],
    "mention_roles": [],
    "attachments": [],
    "embeds": [],
    "timestamp": "2025-11-23T19:48:02.763000+00:00",
    "edited_timestamp": null,
    "flags": 0,
    "components": [],
    "id": "1442240298800386049",
    "channel_id": "1442240298800386049",
    "author": {
      "id": "697171541208596510",
      "username": "penny5746",
      "avatar": "8d191f8254ab5441078bad8c499e1e00",
      "discriminator": "0",
      "public_flags": 0,
      "flags": 0,
      "banner": null,
      "accent_color": null,
      "global_name": "Penny5746",
      "avatar_decoration_data": null,
      "collectibles": null,
      "display_name_styles": null,
      "banner_color": null,
      "clan": null,
      "primary_guild": null
    },
    "pinned": false,
    "mention_everyone": false,
    "tts": false,
    "position": 0
  },
  {
    "type": 0,
    "content": "Sol exhaled through his nose, a slight, amused sound slipping out as he leaned back in his chair and propped his boots on the table.\n\n“Auri,” he said, tone dry but not unkind, “I know what *ecto* is. It’s basically the lifeblood of magic.”\n\nHe gave her that *really, you’re testing me on this?* look, and let a smirk hook one corner of his mouth.\n\n“I’m not dumb, you know.”\n\nAs he spoke, his bracer shimmered, threads of gold, silver, and bronze magic sliding into the air and curling around his fingers like they had minds of their own.\n\nHe caught her watching. Which only encouraged his teasing of her.\n\nWith a quick twist of his wrist, the threads migrated from his fingers and wove into a tiny tree frog that settled itself on top of her notes like they were a leaf. Its skin shifted colors with a magical sheen as its throat ballooned to croak, and its eyes slowly blinked one at a time.\n\n“That’s why theory confuses me,” Sol went on, voice tilting toward playful provocation. “You’re telling me I need to memorize twenty terms to explain something I can already—”\n\nThe frog dissolved into magical threads before reshaping itself into a small ghost that hovered above her resonance tables, as if it were inspecting her work.\n\n“—do,” he finished.\n\nThen, with a bit more flourish than necessary, he let the ghost stretch, compress, and reform into a miniature Auri. This version wore a tiny frown, her tiny braid messy, tail flicking wildly.\n\nSol raised an eyebrow at her.\n\n“Instinct,” he said, almost challengingly. “You make it sound like a liability.”\n\nHe snapped his fingers, causing the illusion to flicker and unravel in a scattering of metallic sparks.\n\n“When really it’s my biggest strength.”\n\nHe took his feet off the table and leaned forward, chin propped in his palm, watching her with open mischief.\n\n“What’s next, *Prof*?” He placed an easy grin on his face, the rivalry in his eyes playful yet sharp.",
    "mentions": [],
    "mention_roles": [],
    "attachments": [],
    "embeds": [],
    "timestamp": "2025-11-23T21:06:58.747000+00:00",
    "edited_timestamp": null,
    "flags": 0,
    "components": [],
    "id": "1442260162957283370",
    "channel_id": "1442240298800386049",
    "author": {
      "id": "155436835013656576",
      "username": "pyroshadow",
      "avatar": "ed853f9f1777de28c22f287e735ce2b1",
      "discriminator": "0",
      "public_flags": 64,
      "flags": 64,
      "banner": null,
      "accent_color": null,
      "global_name": "Nightingale",
      "avatar_decoration_data": {
        "asset": "a_670b722e56740d11d1e6fe55b8094013",
        "sku_id": "1343751617303805983",
        "expires_at": null
      },
      "collectibles": {
        "nameplate": {
          "sku_id": "1377377712028516443",
          "asset": "nameplates/nameplates_v2/spirit_moon/",
          "label": "COLLECTIBLES_NAMEPLATES_V2_SPIRIT_MOON_A11Y",
          "palette": "violet"
        }
      },
      "display_name_styles": {
        "font_id": 8,
        "effect_id": 2,
        "colors": [
          3163762,
          9709528
        ]
      },
      "banner_color": null,
      "clan": {
        "identity_guild_id": "394252141138804736",
        "identity_enabled": true,
        "tag": "RVYN",
        "badge": "6082c2553b03b47ccaea5203567df3cf"
      },
      "primary_guild": {
        "identity_guild_id": "394252141138804736",
        "identity_enabled": true,
        "tag": "RVYN",
        "badge": "6082c2553b03b47ccaea5203567df3cf"
      }
    },
    "pinned": false,
    "mention_everyone": false,
    "tts": false,
    "position": 0
  },
  {
    "type": 0,
    "content": "Auri watched as Sol leaned back in his chair, boots resting on the table. Every fiber of her wanted to snap back with something sharp and playful, but she held herself still, letting him continue as she studied the illusions he created. She had to choose her words carefully if she wanted to be hired as a tutor again, and slowly, she calmed herself. It wasn’t that he didn’t care. He just didn’t realize he *should*.\n\n“Correct. Instinct *is* your strength,” she said evenly. Her voice was calm, but it carried weight. “I won’t argue with you about that.”\n\n“Most magic users think the caster alone shapes the spell,” she continued, twirling her finger in the air, quill stirring in the ink pot. “Intent in, spell out. But it’s not that simple.”\n\n“Ecto responds to three things,\" she said, lifting a finger for each. “Will, resonance, and pattern. Will is the simplest– your natural pull on the energy, the force you bring to make it obey you.” She met his gaze, acknowledging him without flinching. “And yours…is unusually strong.”\n\nAnother finger rose. “Resonance is how deeply you understand the energy, the subtleties you sense instinctually.”\n\nShe held up the third. “Pattern is the important one– the missing piece. Magic doesn’t take just any shape. Your instincts are patterns you’ve memorized without realizing it.”\n\nAuri leaned back, letting the pause stretch just long enough for her words to settle. “That’s why theory matters. Not to teach you *how* to cast, but to see the architecture beneath. If you know the patterns, you can refine them, strengthen them, even create new spells entirely.”",
    "mentions": [],
    "mention_roles": [],
    "attachments": [],
    "embeds": [],
    "timestamp": "2025-11-24T21:10:08.861000+00:00",
    "edited_timestamp": null,
    "flags": 0,
    "components": [],
    "id": "1442623348218658836",
    "channel_id": "1442240298800386049",
    "author": {
      "id": "697171541208596510",
      "username": "penny5746",
      "avatar": "8d191f8254ab5441078bad8c499e1e00",
      "discriminator": "0",
      "public_flags": 0,
      "flags": 0,
      "banner": null,
      "accent_color": null,
      "global_name": "Penny5746",
      "avatar_decoration_data": null,
      "collectibles": null,
      "display_name_styles": null,
      "banner_color": null,
      "clan": null,
      "primary_guild": null
    },
    "pinned": false,
    "mention_everyone": false,
    "tts": false,
    "position": 1
  },
  {
    "type": 0,
    "content": "She slid her notes across the table. They unfurled on their own, words glowing faintly across the parchment. “Of course, if memorizing terms is more what you expected, I can give you my notes. You can recite them before your next exam, word for word. But as you said– you’re not dumb. You can memorize facts.”  \n\n“But when you cast the frog, do you know *how* it happened? The exact patterns you used? If you want to *truly* grasp those concepts, that’s far more important.”\n\nHer eyes flicked to the glowing penmanship. “And far more interesting.”\n\n“So *you* tell *me*, Sol. What’s next?”",
    "mentions": [],
    "mention_roles": [],
    "attachments": [],
    "embeds": [],
    "timestamp": "2025-11-24T21:10:18.688000+00:00",
    "edited_timestamp": null,
    "flags": 0,
    "components": [],
    "id": "1442623389436219565",
    "channel_id": "1442240298800386049",
    "author": {
      "id": "697171541208596510",
      "username": "penny5746",
      "avatar": "8d191f8254ab5441078bad8c499e1e00",
      "discriminator": "0",
      "public_flags": 0,
      "flags": 0,
      "banner": null,
      "accent_color": null,
      "global_name": "Penny5746",
      "avatar_decoration_data": null,
      "collectibles": null,
      "display_name_styles": null,
      "banner_color": null,
      "clan": null,
      "primary_guild": null
    },
    "pinned": false,
    "mention_everyone": false,
    "tts": false,
    "position": 2
  },
  {
    "type": 0,
    "content": "Sol stared at her for a moment, her explanation hanging between them like a puzzle he was supposed to decipher. *Will. Resonance. Pattern.*\n\nHe thought back to the frog. He hadn’t *thought* about any of that. He hadn’t considered resonance or architecture or anything with more structure than a passing impulse. He just pictured the frog, felt a magic well, drew from it, and let it take shape, similar to how a painter makes a masterpiece.\n\nHe blinked, brow creasing slightly.\n\n“That’s the problem, I guess,” he admitted, rubbing the back of his neck. “I don’t think about it.”\n\nHe lifted his hand, watching a faint shimmer of gold-silver-bronze threads roll over his knuckles.\n\n“I honestly couldn’t tell you the last time I said a spell name out loud,” he said, sounding almost embarrassed about it. “Or did a proper somatic anything. Half the time I’m just—” he traced a vague shape in the air, as if drawing a line of light, “—sketching what I want. And the other half, I’m just using enchantment magic to make my words land nicer or,” he shrugged, “to make myself sound like someone people want to follow.”\n\nHe said it plainly, not trying to brag or hide; just being honest. For once, his magic stayed quiet around his fingers.\n\nAuri’s explanation lingered, the idea of patterns and structures tugged at a memory: Lucien’s spellwriting. The memory spell he’d crafted was intricate and deliberate. Nothing about it had been instinct. It had been both art and knowledge.\n\nHe huffed a breath, half reluctant acceptance, half amused surrender, and leaned forward, resting his elbows on the table.\n\n“What’s next,” he said, tilting his head with a teasing grin, “*Prof*, is you teach,” he tapped her notes with one finger, “and I try to understand this nonsense without my brain melting.”",
    "mentions": [],
    "mention_roles": [],
    "attachments": [],
    "embeds": [],
    "timestamp": "2025-11-25T03:03:09.965000+00:00",
    "edited_timestamp": null,
    "flags": 0,
    "components": [],
    "id": "1442712188208025611",
    "channel_id": "1442240298800386049",
    "author": {
      "id": "155436835013656576",
      "username": "pyroshadow",
      "avatar": "ed853f9f1777de28c22f287e735ce2b1",
      "discriminator": "0",
      "public_flags": 64,
      "flags": 64,
      "banner": null,
      "accent_color": null,
      "global_name": "Nightingale",
      "avatar_decoration_data": {
        "asset": "a_670b722e56740d11d1e6fe55b8094013",
        "sku_id": "1343751617303805983",
        "expires_at": null
      },
      "collectibles": {
        "nameplate": {
          "sku_id": "1377377712028516443",
          "asset": "nameplates/nameplates_v2/spirit_moon/",
          "label": "COLLECTIBLES_NAMEPLATES_V2_SPIRIT_MOON_A11Y",
          "palette": "violet"
        }
      },
      "display_name_styles": {
        "font_id": 8,
        "effect_id": 2,
        "colors": [
          3163762,
          9709528
        ]
      },
      "banner_color": null,
      "clan": {
        "identity_guild_id": "394252141138804736",
        "identity_enabled": true,
        "tag": "RVYN",
        "badge": "6082c2553b03b47ccaea5203567df3cf"
      },
      "primary_guild": {
        "identity_guild_id": "394252141138804736",
        "identity_enabled": true,
        "tag": "RVYN",
        "badge": "6082c2553b03b47ccaea5203567df3cf"
      }
    },
    "pinned": false,
    "mention_everyone": false,
    "tts": false,
    "position": 3
  },
  {
    "type": 0,
    "content": "Auri didn’t flinch at the “Prof.” The title slid off her like she’d been called worse, and better, in equal measure. \n\nInstead, she drew her notes back toward her and took out a fresh page before sliding it across the table to the space between them so he could see it. \n\n“Let’s start with Scarboro’s Theory of Three Strands,” she said, calm, deliberate. She dipped her quill and drew an image of three lines woven into a braided cord. “He explained casting spells like weaving a cord with three strands– the three I mentioned earlier. Most casters excel at one or two. For instance, I excel at patterns, but my resonance isn’t as refined. Just remember: Scarboro’s strands. A little alliteration helps with memorization.”\n\nShe leaned forward, eyes glittering with enthusiasm. Although her spells sounded like rote memorization, she genuinely loved talking about magic theory.\n\n“Now, patterns involve words. The word for a moving image would be *lev* for moving, *emma* for image. *Multicolor* is *alacarne*, and *frog* is *cabor*. Put them together, and you have a moving, color-shifting frog. Alter the combination, and the result changes.”\n\nShe paused, letting the idea sink in. \n\n“Simpler commands work if your will is strong enough for the magic to fill in the blanks. I could say *quer* to turn the quill in the ink pot. I don’t have to spell out every action– just focus my intention, and the ecto understands enough to execute it.” Her tail swished as she spoke. “That’s your will at work. You don’t need to study every ‘word’ to project the frog, which is why it feels so effortless and natural. You just need to know the structure well enough to guide your command.”\n\n“Try again,” she said, gesturing to the table. “This time, pay attention to which ‘words’ come to mind as you project the frog. See how your instinct fits into the framework.”",
    "mentions": [],
    "mention_roles": [],
    "attachments": [],
    "embeds": [],
    "timestamp": "2025-11-25T16:10:29.813000+00:00",
    "edited_timestamp": null,
    "flags": 0,
    "components": [],
    "id": "1442910326491316357",
    "channel_id": "1442240298800386049",
    "author": {
      "id": "697171541208596510",
      "username": "penny5746",
      "avatar": "8d191f8254ab5441078bad8c499e1e00",
      "discriminator": "0",
      "public_flags": 0,
      "flags": 0,
      "banner": null,
      "accent_color": null,
      "global_name": "Penny5746",
      "avatar_decoration_data": null,
      "collectibles": null,
      "display_name_styles": null,
      "banner_color": null,
      "clan": null,
      "primary_guild": null
    },
    "pinned": false,
    "mention_everyone": false,
    "tts": false,
    "position": 4
  },
  {
    "type": 0,
    "content": "Sol stared at the page as if it were written in an entirely different language. Which…technically, it was.\n\n“Scarboro’s strands,” he repeated slowly, as if tasting the words would somehow make the theory settle into place. “Right. Three strands. Will, resonance, pattern. Easy.”\n\nIt was *not* easy, his expression revealed all too clearly.\n\nHe lifted his hand anyway, inhaling as if preparing for a dive into cold water.\n\n“Okay. Frog. Color-changing. Uh… *lev…emma…alacarne…*”\nHis brow furrowed.\n“*…cabor.*”\n\nThe magic answered him immediately, naturally, in threads of gold, silver, and bronze, spiraling into the shape of a frog. It appeared on the table, its body pulsing with gentle light like before.\n\nSol stared at it. He tried to picture “multicolor.” Tried to fit the new “words” into the instinct he typically followed.\n\nHe cleared his throat.\n\n“*Levvema…alacarna…caber?*”\n\nThe frog did *not* shift colors. Instead, its legs dramatically elongated until it was a stilt-legged, lanky creature nearly the height of the ink pot. It blinked slowly, hollow-eyed, before letting out a shrill *kreee—eeeeek* that echoed across the table with far too much volume for something so small.\n\nSol flinched.\n\n“Okay, nope, nope, that’s wrong,” he said quickly, reaching forward and snatching the illusion in both hands. The frog wobbled on its ridiculous stilts and fell over, legs folding like collapsing scaffolding, before dissolving entirely in a puff of sparks.\n\nHe sat very still for a moment. Then he looked at Auri.\n\n“…So. How’d I do?”\n\nIt was the most hopeful and hopeless look he’d ever given her.",
    "mentions": [],
    "mention_roles": [],
    "attachments": [],
    "embeds": [],
    "timestamp": "2025-11-25T20:33:32.493000+00:00",
    "edited_timestamp": "2025-11-25T20:34:04.670000+00:00",
    "flags": 0,
    "components": [],
    "id": "1442976523849039937",
    "channel_id": "1442240298800386049",
    "author": {
      "id": "155436835013656576",
      "username": "pyroshadow",
      "avatar": "ed853f9f1777de28c22f287e735ce2b1",
      "discriminator": "0",
      "public_flags": 64,
      "flags": 64,
      "banner": null,
      "accent_color": null,
      "global_name": "Nightingale",
      "avatar_decoration_data": {
        "asset": "a_670b722e56740d11d1e6fe55b8094013",
        "sku_id": "1343751617303805983",
        "expires_at": null
      },
      "collectibles": {
        "nameplate": {
          "sku_id": "1377377712028516443",
          "asset": "nameplates/nameplates_v2/spirit_moon/",
          "label": "COLLECTIBLES_NAMEPLATES_V2_SPIRIT_MOON_A11Y",
          "palette": "violet"
        }
      },
      "display_name_styles": {
        "font_id": 8,
        "effect_id": 2,
        "colors": [
          3163762,
          9709528
        ]
      },
      "banner_color": null,
      "clan": {
        "identity_guild_id": "394252141138804736",
        "identity_enabled": true,
        "tag": "RVYN",
        "badge": "6082c2553b03b47ccaea5203567df3cf"
      },
      "primary_guild": {
        "identity_guild_id": "394252141138804736",
        "identity_enabled": true,
        "tag": "RVYN",
        "badge": "6082c2553b03b47ccaea5203567df3cf"
      }
    },
    "pinned": false,
    "mention_everyone": false,
    "tts": false,
    "position": 5
  },
  {
    "type": 0,
    "content": "Auri let the frog collapse and dissolve, her face composed, but the corner of her mouth twitched slightly, just enough to betray a suppressed laugh. She cleared her throat and smoothed her notes. \n\n“You didn’t fail,” she said evenly, though her eyes sparkled faintly. “You just…tried to force the spell to follow the words instead of your instinct. Remember, it’s *three strands*, not one.”\n\nShe leaned forward, resting her forearms on the table. “Cast it like you normally would. Don’t worry about pronouncing the components perfectly. Just pay attention to which ones your mind reaches for on its own.”\n\nHer amber eyes shone with pure enjoyment. This was the part she loved the most. “So go ahead. Make the frog again. This time, *your way*, and pay attention to what happens– which words your mind chooses.”",
    "mentions": [],
    "mention_roles": [],
    "attachments": [],
    "embeds": [],
    "timestamp": "2025-11-26T19:42:40.081000+00:00",
    "edited_timestamp": null,
    "flags": 0,
    "components": [],
    "id": "1443326108971040769",
    "channel_id": "1442240298800386049",
    "author": {
      "id": "697171541208596510",
      "username": "penny5746",
      "avatar": "8d191f8254ab5441078bad8c499e1e00",
      "discriminator": "0",
      "public_flags": 0,
      "flags": 0,
      "banner": null,
      "accent_color": null,
      "global_name": "Penny5746",
      "avatar_decoration_data": null,
      "collectibles": null,
      "display_name_styles": null,
      "banner_color": null,
      "clan": null,
      "primary_guild": null
    },
    "pinned": false,
    "mention_everyone": false,
    "tts": false,
    "position": 6
  },
  {
    "type": 0,
    "content": "Sol exhaled slowly and rolled his shoulders back. He let the embarrassment fade, letting the static in his head settle.\n\n“Okay,” he muttered to himself. He gave Auri a nervous smile, “My way.”\n\nThis time, he reached for the *image* instead of stressing over words.\n\nThreads of gold, silver, and bronze slipped free from his fingers, curling lazily through the air like smoke caught in sunlight.\n\nThe frog retook shape on the table. It was smaller than before, much brighter in color, and glossy-eyed, breathing in tiny, rhythmic pulses. Perfectly mundane for something born of magic.\n\nSol leaned closer, studying it with focus.\n\n“Alright,” he whispered. “Move.”\n\nThe frog hopped. Clean. Simple. No distortion. \n\nHe smiled faintly and began to concentrate again to try something else. He pictured the emerald green of the skin turning sapphire blue like a beetle shell.\n\n“Blue.”\n\nFor just a fraction of a second, nothing happened. Then softly, like pigment soaking into paper, the frog’s green skin changed, sliding slowly into a rich, inky blue.\n\nSol blinked. Behind his eyes, something *shifted*. For the first time, faint echoes surfaced, half-formed words brushing against his thoughts like whispers from another room: *emma…cabor…alacarna.*\n\nHe stiffened slightly. “Oh,” he said in surprise. “I can hear it,” he murmured. “It feels like the words are there, like they’re hovering around me, and I can just grab them instead of speaking!”\n\nHe waved a finger gently near the frog, and it croaked softly in response, low and real enough to be convincing.\n\n“That’s…” his mouth quirked, “…actually kind of cool.”\n\nSol held on to that strange new awareness of the half-heard echo of words brushing the edges of his thoughts. \n\nThe frog shifted its tiny feet on the table. “Okay,” he said quietly, more to himself than to her. “Don’t lose it.”\n\nHe inhaled, slow and steady. He didn’t picture another frog at first. He pictured *one* thing becoming *many*.\n\nHe remembered Auri’s lesson. Three strands: will, resonance, pattern. His jaw tightened as he focused. *Will*, the pull in his chest, that familiar warmth like a tide behind his ribs. *Resonance*, the way the magic hummed when he looked at the frog, that subtle frequency in his bones. *Pattern*, a shape in his mind, a map just beneath the image.\n\n“One more trick,” he whispered.\n\nThe magical threads stirred again, delicate and precise instead of wild. The frog on the table shimmered before it cleanly split in twain.\n\nTwo frogs now sat side by side, identical in every detail down to the faint rise and fall of their chests.\n\nSol stared at them for a heartbeat, stunned. “It worked,” he cackled.\n\nEncouraged, he lifted his hand again, glancing briefly at Auri. “What about there?”\n\nA third weave of light spun upwards, and a tiny blue frog appeared against her collarbone, blinking serenely like it belonged there.\n\nSol smiled the widest smile he’s had in a while, his eyes lighting up with a new, invigorated sense of purpose.",
    "mentions": [],
    "mention_roles": [],
    "attachments": [],
    "embeds": [],
    "timestamp": "2025-11-27T20:06:28.154000+00:00",
    "edited_timestamp": null,
    "flags": 0,
    "components": [],
    "id": "1443694486608675058",
    "channel_id": "1442240298800386049",
    "author": {
      "id": "155436835013656576",
      "username": "pyroshadow",
      "avatar": "ed853f9f1777de28c22f287e735ce2b1",
      "discriminator": "0",
      "public_flags": 64,
      "flags": 64,
      "banner": null,
      "accent_color": null,
      "global_name": "Nightingale",
      "avatar_decoration_data": {
        "asset": "a_670b722e56740d11d1e6fe55b8094013",
        "sku_id": "1343751617303805983",
        "expires_at": null
      },
      "collectibles": {
        "nameplate": {
          "sku_id": "1377377712028516443",
          "asset": "nameplates/nameplates_v2/spirit_moon/",
          "label": "COLLECTIBLES_NAMEPLATES_V2_SPIRIT_MOON_A11Y",
          "palette": "violet"
        }
      },
      "display_name_styles": {
        "font_id": 8,
        "effect_id": 2,
        "colors": [
          3163762,
          9709528
        ]
      },
      "banner_color": null,
      "clan": {
        "identity_guild_id": "394252141138804736",
        "identity_enabled": true,
        "tag": "RVYN",
        "badge": "6082c2553b03b47ccaea5203567df3cf"
      },
      "primary_guild": {
        "identity_guild_id": "394252141138804736",
        "identity_enabled": true,
        "tag": "RVYN",
        "badge": "6082c2553b03b47ccaea5203567df3cf"
      }
    },
    "pinned": false,
    "mention_everyone": false,
    "tts": false,
    "position": 7,
    "reactions": [
      {
        "emoji": {
          "id": null,
          "name": "🤩"
        },
        "count": 1,
        "count_details": {
          "burst": 0,
          "normal": 1
        },
        "burst_colors": [],
        "me_burst": false,
        "burst_me": false,
        "me": false,
        "burst_count": 0
      }
    ]
  },
  {
    "type": 0,
    "content": "Auri’s lips curved into a small, satisfied smile as the frogs hopped around the table.  Watching them move, watching Sol work with the threads— was almost hypnotic. His illusions didn’t just *function* the way her carefully structured spells did; they *breathed.*\n\n“They’re adorable,” she said softly, reaching out to boop one of the tiny frogs on the nose. It blinked, startled, then croaked. A faint warmth tugged at her chest. “I’ve always liked frogs.”\n\nShe straightened, smoothing her notes absentmindedly as she studied the moving, shimmering shapes. “Impressive,” she murmured. “The way you let the strands guide each other. Your magic feels…alive, not just functional. There’s thought in every thread, and yet it flows naturally.”\n\nA quiet breath slipped out of her. She glanced down at her own meticulously aligned diagrams, the ink neat and precise.\n\n“I know I’m here to tutor *you*,” she said, voice measured but soft, warm with curiosity, “but… would you be willing to show me how you approach it?”\n\nHer tail flicked subtly behind her as she met his eyes. “I understand that will is tied to a caster’s sense of passion. I have passion. Very particular things I care about...but my professor told me once that passion isn’t something that can be taught.”\n\nShe tilted her head slightly, hands folded over her notes. “…Do you think that’s true?”",
    "mentions": [],
    "mention_roles": [],
    "attachments": [],
    "embeds": [],
    "timestamp": "2025-11-28T22:55:40.393000+00:00",
    "edited_timestamp": null,
    "flags": 0,
    "components": [],
    "id": "1444099456051183699",
    "channel_id": "1442240298800386049",
    "author": {
      "id": "697171541208596510",
      "username": "penny5746",
      "avatar": "8d191f8254ab5441078bad8c499e1e00",
      "discriminator": "0",
      "public_flags": 0,
      "flags": 0,
      "banner": null,
      "accent_color": null,
      "global_name": "Penny5746",
      "avatar_decoration_data": null,
      "collectibles": null,
      "display_name_styles": null,
      "banner_color": null,
      "clan": null,
      "primary_guild": null
    },
    "pinned": false,
    "mention_everyone": false,
    "tts": false,
    "position": 8
  },
  {
    "type": 0,
    "content": "Sol’s smile warmed around the edges, all forms of teasing and cockiness replaced with genuine excitement. He’d been asked this question many times before, and it was one of his favorite ones to answer.\n\n“Your professor’s *not* wrong,” he said matter-of-factly. “His wording’s just incomplete.”\n\nWith a slight motion of his hand, the frogs on the table unraveled one by one into quiet threads of light until only the tiny blue frog on Auri’s shoulder remained.\n\n“You can’t *teach* passion,” Sol continued. “But that doesn’t mean people don’t have it; it just means not everyone has discovered theirs yet.”\n\nHe stood, brushing his hands together to center himself.\n\n“Most of us spend half our lives looking for the thing that makes our chest feel like it’s going to split open in the best ways.”\n\nHe lifted his hands, magic swirling around them in a galaxy of colors, and his bag on the table stirred. After a few seconds, the zippers sighed open, and from inside emerged: colorful fabrics, spools of thread, shimmering needles, silvery chalk, and paper templates. Everything spilled into the air around Auri in a slow orbit of gold and silver light.\n\nA tape measure slipped loose from one of the bag’s side pockets, moving with a mind of its own. It floated gently around her shoulders and arms, then looped around her waist with absolute professionalism, never tugging or being invasive. It looked as if the tape measure had psychically transferred Auri’s measurements over to Sol before it quietly slinked back into the small pocket.\n\n“That,” Sol said quietly, eyes tracing the motion of every moving piece, “is fashion, for me.”\n\nAs he spoke, the design templates aligned themselves in midair. Fabrics folded and snipped themselves without scissors, and needles darted in smooth arcs, stitching as though guided by invisible hands.\n\n“When I find a design I *love*, it’s exciting and addictive,” he admitted excitedly. “But it can also be infuriating.”\n\nHe smiled faintly at his friend. “It happens when your brain can already see what you want, but your hands just can’t get there fast enough. But eventually—”\n\nThreads began embroidering the front of the forming shirt. A tiny frog slowly bloomed, stitched in luminous green and blue threads that shifted with the light. The frog on Auri’s shoulder twitched as if it had just become aware that it had just been copied.\n\n“—You start realizing you’d rather fight that frustration every day than do something else boringly easy.”\n\nThe fabric completed itself in a quiet shimmer. He snapped his fingers once, and the tools, cloth, thread, and templates all folded gracefully back into his bag as if they’d never left.\n\nSol held out the finished shirt to Auri: a black, off-the-shoulder crop top with a luminescent green and blue tree frog embroidered on the front.\n\n“That’s what passion is,” he said. “It’s not just something you’re born with, it’s something you *discover* and still love even after you realize you’ll sometimes suffer doing it.”\n\nHe softened his voice and addressed Auri, “And if you think you haven’t found yours yet, it doesn’t mean it isn’t there.”\n\nHe glanced at the frog still perched on her shoulder. “It just means it hasn’t jumped in front of you yet.”",
    "mentions": [],
    "mention_roles": [],
    "attachments": [],
    "embeds": [],
    "timestamp": "2025-11-29T05:33:59.639000+00:00",
    "edited_timestamp": null,
    "flags": 0,
    "components": [],
    "id": "1444199696754147389",
    "channel_id": "1442240298800386049",
    "author": {
      "id": "155436835013656576",
      "username": "pyroshadow",
      "avatar": "ed853f9f1777de28c22f287e735ce2b1",
      "discriminator": "0",
      "public_flags": 64,
      "flags": 64,
      "banner": null,
      "accent_color": null,
      "global_name": "Nightingale",
      "avatar_decoration_data": {
        "asset": "a_670b722e56740d11d1e6fe55b8094013",
        "sku_id": "1343751617303805983",
        "expires_at": null
      },
      "collectibles": {
        "nameplate": {
          "sku_id": "1377377712028516443",
          "asset": "nameplates/nameplates_v2/spirit_moon/",
          "label": "COLLECTIBLES_NAMEPLATES_V2_SPIRIT_MOON_A11Y",
          "palette": "violet"
        }
      },
      "display_name_styles": {
        "font_id": 8,
        "effect_id": 2,
        "colors": [
          3163762,
          9709528
        ]
      },
      "banner_color": null,
      "clan": {
        "identity_guild_id": "394252141138804736",
        "identity_enabled": true,
        "tag": "RVYN",
        "badge": "6082c2553b03b47ccaea5203567df3cf"
      },
      "primary_guild": {
        "identity_guild_id": "394252141138804736",
        "identity_enabled": true,
        "tag": "RVYN",
        "badge": "6082c2553b03b47ccaea5203567df3cf"
      }
    },
    "pinned": false,
    "mention_everyone": false,
    "tts": false,
    "position": 9
  },
  {
    "type": 0,
    "content": "Auri listened in stillness, not the rehearsed academic poise she had practiced prior to the tutoring session. As the fabric rose and folded itself, as colors stitched into shape with a kind of living intention, she forgot entirely to school her expression. Wonder softened the sharp lines of her focus. \n\nWhen Sol offered her the finished shirt, she took it carefully in both hands, as if it were something sacred. \n\n“It’s…so cute,” she said quietly. Her voice had none of the clipped professionalism she carried earlier; it was warm, almost shy. She brushed her thumb over the tiny embroidered frog, its shifting green-blue threads catching the lamplight. “You made this for me…thank you.”\n\nThe frog illusion on her shoulder let out a soft croak, and Auri huffed a tiny laugh through her nose before lifting a finger to gently nuzzle its cheek. \n\n“I think you’re right,” she admitted, eyes still lingering on the embroidery. “About passion. About discovering it instead of being born knowing.” She lowered the shirt to her lap, smoothing the hem with a sweep of her palm. “I wasn’t born loving magic, books, or…knowing what I wanted to do with my life. There were specific moments that sparked those flames.”\n\n“I’ve been trying to learn something called a bladesong,” she continued. “My friend told me it’s like…feeling music. And—” she exhaled in a frustrated little breath, “I can *understand* the theory perfectly. I can study the ability, understand what it’s supposed to *do*.”\n\n“But I can’t seem to *feel* it. Not the way I’m supposed to.” Her voice dropped to a low murmur. “And when my professor said you can’t teach passion, I…I was worried that meant I couldn’t learn it, but…I’m not very good at giving up on things.”",
    "mentions": [],
    "mention_roles": [],
    "attachments": [],
    "embeds": [],
    "timestamp": "2025-12-02T22:24:34.615000+00:00",
    "edited_timestamp": null,
    "flags": 0,
    "components": [],
    "id": "1445541181873455204",
    "channel_id": "1442240298800386049",
    "author": {
      "id": "697171541208596510",
      "username": "penny5746",
      "avatar": "8d191f8254ab5441078bad8c499e1e00",
      "discriminator": "0",
      "public_flags": 0,
      "flags": 0,
      "banner": null,
      "accent_color": null,
      "global_name": "Penny5746",
      "avatar_decoration_data": null,
      "collectibles": null,
      "display_name_styles": null,
      "banner_color": null,
      "clan": null,
      "primary_guild": null
    },
    "pinned": false,
    "mention_everyone": false,
    "tts": false,
    "position": 10
  },
  {
    "type": 0,
    "content": "The frog on her shoulder hopped once and settled again, and Auri stroked its head with a small, absent tenderness.\n\n“But the way you talked about your designs…” She looked up at him fully now, respect in her eyes. “The way you *lit up* when you showed me…”\n\nShe placed a hand over her sternum, as though grounding herself there. \n\n“It made me think maybe I just haven’t found the right way to let the music in.” Her brows knit delicately. “So how do I do that? Where do I even start looking?”\n\nShe smiled— gentle, a little uncertain, but hopeful all the same. “You said passion is something that jumps in front of you. I guess I just…don’t know where my answer is hiding.”",
    "mentions": [],
    "mention_roles": [],
    "attachments": [],
    "embeds": [],
    "timestamp": "2025-12-02T22:24:39.819000+00:00",
    "edited_timestamp": null,
    "flags": 0,
    "components": [],
    "id": "1445541203700482219",
    "channel_id": "1442240298800386049",
    "author": {
      "id": "697171541208596510",
      "username": "penny5746",
      "avatar": "8d191f8254ab5441078bad8c499e1e00",
      "discriminator": "0",
      "public_flags": 0,
      "flags": 0,
      "banner": null,
      "accent_color": null,
      "global_name": "Penny5746",
      "avatar_decoration_data": null,
      "collectibles": null,
      "display_name_styles": null,
      "banner_color": null,
      "clan": null,
      "primary_guild": null
    },
    "pinned": false,
    "mention_everyone": false,
    "tts": false,
    "position": 11
  },
  {
    "type": 0,
    "content": "Sol noticed the way Auri’s voice softened, and he found himself smiling at her.\n\n“It’s no problem by the way,” he added, nodding toward the shirt. “I like making things for people. It’s kind of my thing.”\n\nHe glanced back at her with thoughtful eyes. “As for your passion?” he mused. “I don’t think it’s hiding nearly as far away as you think.” A slight grin tugged at his lips. “Maybe it already jumped in front of you.” He tilted his head slightly, studying her, like he was creating a new design. “And you just didn’t recognize it,” he said slowly.\n\nBefore Auri could ask what he meant, he met her eyes and stood up suddenly, a spark of energy in his eyes. With a sweep of his arms across the table in one smooth motion, Sol sent books and parchment sliding aside in a cluster of soft thuds and shuffling paper. Then, without hesitation, he climbed up onto it, settling cross-legged, perfectly unbothered by the stares he probably just earned.\n\nHe patted the spot across from him and held out both hands to her. “Come on,” he said brightly. “Get up here. I’ve got an idea.”",
    "mentions": [],
    "mention_roles": [],
    "attachments": [],
    "embeds": [],
    "timestamp": "2025-12-03T04:01:10.065000+00:00",
    "edited_timestamp": null,
    "flags": 0,
    "components": [],
    "id": "1445625887730172045",
    "channel_id": "1442240298800386049",
    "author": {
      "id": "155436835013656576",
      "username": "pyroshadow",
      "avatar": "ed853f9f1777de28c22f287e735ce2b1",
      "discriminator": "0",
      "public_flags": 64,
      "flags": 64,
      "banner": null,
      "accent_color": null,
      "global_name": "Nightingale",
      "avatar_decoration_data": {
        "asset": "a_670b722e56740d11d1e6fe55b8094013",
        "sku_id": "1343751617303805983",
        "expires_at": null
      },
      "collectibles": {
        "nameplate": {
          "sku_id": "1377377712028516443",
          "asset": "nameplates/nameplates_v2/spirit_moon/",
          "label": "COLLECTIBLES_NAMEPLATES_V2_SPIRIT_MOON_A11Y",
          "palette": "violet"
        }
      },
      "display_name_styles": {
        "font_id": 8,
        "effect_id": 2,
        "colors": [
          3163762,
          9709528
        ]
      },
      "banner_color": null,
      "clan": {
        "identity_guild_id": "394252141138804736",
        "identity_enabled": true,
        "tag": "RVYN",
        "badge": "6082c2553b03b47ccaea5203567df3cf"
      },
      "primary_guild": {
        "identity_guild_id": "394252141138804736",
        "identity_enabled": true,
        "tag": "RVYN",
        "badge": "6082c2553b03b47ccaea5203567df3cf"
      }
    },
    "pinned": false,
    "mention_everyone": false,
    "tts": false,
    "position": 12,
    "reactions": [
      {
        "emoji": {
          "id": null,
          "name": "🤩"
        },
        "count": 1,
        "count_details": {
          "burst": 0,
          "normal": 1
        },
        "burst_colors": [],
        "me_burst": false,
        "burst_me": false,
        "me": false,
        "burst_count": 0
      }
    ]
  },
  {
    "type": 0,
    "content": "Auri blinked when he swept the table clean, not from shock but from the spark of *oh, we’re doing this right* ***now***. The old version of her— stern posture, tidy notes, carefully controlled tone— would’ve protested.\n\nBut that version of her had slipped away somewhere between the frog illusion and the little embroidered one staring up at her from her lap. \n\nShe slid off her chair and began calmly gathering the displaced books and parchment. She didn’t rush, just stacked the papers into a neat pile, squared the edges with a practiced tap and set them safely at the table’s corner…as though climbing onto furniture mid-lesson was simply the next logical step in the syllabus.\n\nOnly then did she lift her gaze to Sol, still cross-legged and holding his hands out like she should’ve been up there already. \n\n“Alright. I’m coming.” \n\nShe set the embroidered shirt aside with care, placed her fingers in his, and let him help her up. She pulled herself onto the table across from him with surprising grace. Her tail curled into the shape of a question mark, her amber eyes bright with curiosity. \n\n“Okay, Sol,” she said, settling into the mirrored cross-legged posture. “What’s this idea of yours?”\n\nThere was no trace of the version of her who had walked into the room aside from the organization, but that was simply who Auri was. Everything else was trust, curiosity, and maybe the beginning of what she’d been searching for.",
    "mentions": [],
    "mention_roles": [],
    "attachments": [],
    "embeds": [],
    "timestamp": "2025-12-04T04:11:02.385000+00:00",
    "edited_timestamp": "2025-12-04T04:11:16.039000+00:00",
    "flags": 0,
    "components": [],
    "id": "1445990759965790382",
    "channel_id": "1442240298800386049",
    "author": {
      "id": "697171541208596510",
      "username": "penny5746",
      "avatar": "8d191f8254ab5441078bad8c499e1e00",
      "discriminator": "0",
      "public_flags": 0,
      "flags": 0,
      "banner": null,
      "accent_color": null,
      "global_name": "Penny5746",
      "avatar_decoration_data": null,
      "collectibles": null,
      "display_name_styles": null,
      "banner_color": null,
      "clan": null,
      "primary_guild": null
    },
    "pinned": false,
    "mention_everyone": false,
    "tts": false,
    "position": 13
  },
  {
    "type": 0,
    "content": "Sol’s fingers closed gently around hers, his thumb resting warmly against her knuckles, as she settled across from him. His voice dropped into a low, steady tone.\n\n“Okay,” he said quietly. “Close your eyes, let the room fall away around you, and just focus on my words. Shut everything else out.”\n\nHe gave her hands a slight, reassuring squeeze.\n\n“I want you to think about a memory,” he continued. “Not just a regular one, not something impressive because other people *say* it is.”\n\nA faint smile colored his voice. “Your favorite one.”\n\nHe leaned in just a little. “Tell me about it,” he said softly. “Where were you? What was happening around you?  What does the air *smell* like? What does it *sound* like—are there voices, music, silence?”\n\nHe paused, letting the images form in her mind. “How did it feel? In your chest. In your stomach. In your throat. In your *mind*. Was it warm or cold? Light or heavy? Were you standing still or nervous?”\n\nA pause filled the space, gentle and unrushed.\n\n“And the important one,” he added more quietly. “Why is *that* one your favorite?”\n\nHe held her hands tightly like an anchor waiting for her response.",
    "mentions": [],
    "mention_roles": [],
    "attachments": [],
    "embeds": [],
    "timestamp": "2025-12-04T21:29:45.774000+00:00",
    "edited_timestamp": "2025-12-05T08:15:03.162000+00:00",
    "flags": 0,
    "components": [],
    "id": "1446252163205431419",
    "channel_id": "1442240298800386049",
    "author": {
      "id": "155436835013656576",
      "username": "pyroshadow",
      "avatar": "ed853f9f1777de28c22f287e735ce2b1",
      "discriminator": "0",
      "public_flags": 64,
      "flags": 64,
      "banner": null,
      "accent_color": null,
      "global_name": "Nightingale",
      "avatar_decoration_data": {
        "asset": "a_670b722e56740d11d1e6fe55b8094013",
        "sku_id": "1343751617303805983",
        "expires_at": null
      },
      "collectibles": {
        "nameplate": {
          "sku_id": "1377377712028516443",
          "asset": "nameplates/nameplates_v2/spirit_moon/",
          "label": "COLLECTIBLES_NAMEPLATES_V2_SPIRIT_MOON_A11Y",
          "palette": "violet"
        }
      },
      "display_name_styles": {
        "font_id": 8,
        "effect_id": 2,
        "colors": [
          3163762,
          9709528
        ]
      },
      "banner_color": null,
      "clan": {
        "identity_guild_id": "394252141138804736",
        "identity_enabled": true,
        "tag": "RVYN",
        "badge": "6082c2553b03b47ccaea5203567df3cf"
      },
      "primary_guild": {
        "identity_guild_id": "394252141138804736",
        "identity_enabled": true,
        "tag": "RVYN",
        "badge": "6082c2553b03b47ccaea5203567df3cf"
      }
    },
    "pinned": false,
    "mention_everyone": false,
    "tts": false,
    "position": 14,
    "reactions": [
      {
        "emoji": {
          "id": null,
          "name": "❤️"
        },
        "count": 1,
        "count_details": {
          "burst": 0,
          "normal": 1
        },
        "burst_colors": [],
        "me_burst": false,
        "burst_me": false,
        "me": false,
        "burst_count": 0
      }
    ]
  },
  {
    "type": 0,
    "content": "Auri’s fingers tightened around his just slightly, like she was bracing herself before stepping into a familiar but fragile place, exactly as he had asked her to. Her eyes slipped closed.\n\n“I…already know which memory it is,” she murmured, her voice slipping easily into the quiet space he created for her.\n\nHer voice softened further, as if the room around them truly had fallen away and the two of them were suspended somewhere outside the hush of the library. \n\n“The day I arrived at the tower.” \n\nShe drew in a slow, steadying breath.\n\n“It was raining. The kind that makes everything smell like wet stone and old earth. Darian brought me to the door and…I knew he was taking me there to stay.”\n\nShe shifted a little, shoulders curling inward as though she was once again that small, uncertain girl. Her fingers flexed in Sol’s, grounding herself with the anchor he offered.\n\n“We climbed the tower stairs, spiraling forever upward, and I remember thinking that the higher we went, the more the world below felt like it was slipping away. At the top, Artorius was waiting for us.” She let out a soft chuckle. “I said something that was kind of rude. I didn’t know any better. But…he wasn’t angry.”\n\nHer hands squeezed his as the memory deepened, warmed by something that felt like warmth and ache woven together. \n\n“Darian left me much sooner than I expected. He was the one who found me alone in that ruin. The first person who showed me kindness. So when he turned to go, I—” Her voice caught. “I tried not to cry. I really did.”\n\nShe swallowed, then continued. \n\n“Artorius saw it. He conjured a flower. A glowing one. Blue petals that shimmered like moonlight.”\n\nA small, soft smile touched her lips.\n\n“I’d never seen magic used like that before. When Darian used it, it was always practical, or cautioned as something dangerous. But this…this was just kindness. A spell created for no reason except to make a frightened child feel less alone.”",
    "mentions": [],
    "mention_roles": [],
    "attachments": [],
    "embeds": [],
    "timestamp": "2025-12-08T23:50:14.239000+00:00",
    "edited_timestamp": null,
    "flags": 0,
    "components": [],
    "id": "1447737066212298903",
    "channel_id": "1442240298800386049",
    "author": {
      "id": "697171541208596510",
      "username": "penny5746",
      "avatar": "8d191f8254ab5441078bad8c499e1e00",
      "discriminator": "0",
      "public_flags": 0,
      "flags": 0,
      "banner": null,
      "accent_color": null,
      "global_name": "Penny5746",
      "avatar_decoration_data": null,
      "collectibles": null,
      "display_name_styles": null,
      "banner_color": null,
      "clan": null,
      "primary_guild": null
    },
    "pinned": false,
    "mention_everyone": false,
    "tts": false,
    "position": 15
  },
  {
    "type": 0,
    "content": "The memory revealed itself to Sol as she spoke, allowing him to see it exactly as she once did: Darian— human, in his thirties, with tired eyes and messy, brown hair. And Artorius— tall and composed, adorned in a hooded cloak tattered by the ages and singed at the edges. From certain angles his hood pulled shadow across his features, revealing the faint, cold flicker of blue flame where eyes should be. A skeletal face, impossible but serene. A figure woven from contradictions: benevolent yet terrifying, warm yet carved from death’s quiet. \n\n“That’s why it’s my favorite memory,” Auri continued, seemingly unaware of what Sol might be seeing through her. “Because it’s when everything wrong in my life stopped feeling permanent. When the girl with no memories and no name finally felt like the world might have a place just for her.”",
    "mentions": [],
    "mention_roles": [],
    "attachments": [],
    "embeds": [],
    "timestamp": "2025-12-08T23:50:27.255000+00:00",
    "edited_timestamp": null,
    "flags": 0,
    "components": [],
    "id": "1447737120805355684",
    "channel_id": "1442240298800386049",
    "author": {
      "id": "697171541208596510",
      "username": "penny5746",
      "avatar": "8d191f8254ab5441078bad8c499e1e00",
      "discriminator": "0",
      "public_flags": 0,
      "flags": 0,
      "banner": null,
      "accent_color": null,
      "global_name": "Penny5746",
      "avatar_decoration_data": null,
      "collectibles": null,
      "display_name_styles": null,
      "banner_color": null,
      "clan": null,
      "primary_guild": null
    },
    "pinned": false,
    "mention_everyone": false,
    "tts": false,
    "position": 16
  },
  {
    "type": 0,
    "content": "As Auri spoke, Sol’s eyes slowly drifted shut; he concentrated intensely and slowed his breathing. He let her words paint themselves in his mind, each detail displayed like color on canvas: the damp stones, spiraling stairs, towering bookshelves, a man of shadow and blue flame offering a flower.\n\nHis magic stirred, and a soft warmth filled his bracer. A glow like metal heated in a forge lit up the bracer as threads of gold, silver, and bronze magic seeped from the carved detailing, rising into the air in thin filaments. At first, they hovered uncertainly above his skin, then, sensing Auri’s memory unfold, they drifted forward.\n\nThey curled around his fingers in slow spirals of light, and when they reached hers, the magical threads wrapped their joined hands, gently lacing them together. The strands wove over and under one another with the delicacy of a spider spinning its web. They climbed in soft loops up their wrists, their glow pulsing in tandem with their heartbeats.\n\nSol’s brow twitched, the images forming behind his eyelids, and he whispered: “Keep going.”\n\nBy the time she finished her memory, the air around them had begun to shift. It thickened with static, a breath of power coiling in the space between them. Then a breeze stirred gently around them. At first, it caught the edges of their hair and shifted a few book pages. Then it grew: papers and quills around them quivered, then rose weightlessly through the air, caught in an invisible current that spiraled slowly around their bodies. Scrolls unfurled slightly as they floated, drifting like soft banners. The wind circled them in widening loops, subtle at first, then more insistent. An unmistakable rising swell of magic followed it.",
    "mentions": [],
    "mention_roles": [],
    "attachments": [],
    "embeds": [],
    "timestamp": "2025-12-10T04:31:24.303000+00:00",
    "edited_timestamp": null,
    "flags": 0,
    "components": [],
    "id": "1448170212254941184",
    "channel_id": "1442240298800386049",
    "author": {
      "id": "155436835013656576",
      "username": "pyroshadow",
      "avatar": "ed853f9f1777de28c22f287e735ce2b1",
      "discriminator": "0",
      "public_flags": 64,
      "flags": 64,
      "banner": null,
      "accent_color": null,
      "global_name": "Nightingale",
      "avatar_decoration_data": {
        "asset": "a_670b722e56740d11d1e6fe55b8094013",
        "sku_id": "1343751617303805983",
        "expires_at": null
      },
      "collectibles": {
        "nameplate": {
          "sku_id": "1377377712028516443",
          "asset": "nameplates/nameplates_v2/spirit_moon/",
          "label": "COLLECTIBLES_NAMEPLATES_V2_SPIRIT_MOON_A11Y",
          "palette": "violet"
        }
      },
      "display_name_styles": {
        "font_id": 8,
        "effect_id": 2,
        "colors": [
          3163762,
          9709528
        ]
      },
      "banner_color": null,
      "clan": {
        "identity_guild_id": "394252141138804736",
        "identity_enabled": true,
        "tag": "RVYN",
        "badge": "6082c2553b03b47ccaea5203567df3cf"
      },
      "primary_guild": {
        "identity_guild_id": "394252141138804736",
        "identity_enabled": true,
        "tag": "RVYN",
        "badge": "6082c2553b03b47ccaea5203567df3cf"
      }
    },
    "pinned": false,
    "mention_everyone": false,
    "tts": false,
    "position": 17
  },
  {
    "type": 0,
    "content": "He inhaled deeply and leaned into the magic surge, letting the memory Auri shared become a blueprint for the spell taking form. The threads around their arms flared brightly like a supernova. Then, with a smooth pull upward, like someone tugging a rope of light, the magic shot toward the ceiling.\n\nThe threads twisted and braided in the air, thickening into luminous ribbons that unfurled into a spiraling column above them. It widened rapidly, blooming outward in a sweeping arc of colors until it curved down, forming a dome of interwoven light.\n\nSuddenly, the floor beneath them quivered. A ripple originating from their crossed legs spread outwards, distorting the wooden boards as though they were reflections in a lake. The wood darkened, the grain dissolving into cold, wet stone. The rain's sheen slickened the surface with ghostly moisture.\n\nThe walls shifted next. Their boundaries melted grain by grain, as if someone were erasing them with slow, deliberate strokes of an eraser. The shelves around them elongated and twisted upward into spiraling brick walls. Grooves of ancient stone revealed themselves as steps, ascending endlessly into a tower that seemed to have no end.\n\nShadows stretched and folded like living ink, shaping the imprint of narrow windows rattling softly with storm wind.\n\nA distant creak sounded, followed by the echoes of feet going up narrow steps. A man’s low voice hummed, low, warm, and familiar. Then a child’s shaky breath expelled into the air; it was tinged with both fear and wonder.\n\nThe ceiling continued to recede, stretching higher and higher until the wooden rafters vanished, replaced by the curved stone arch of the tower’s upper chamber. Raindrops pattered faintly against unseen walls.\n\nThen a soft, cold, blue glow pulsed across the chamber. It gathered at the far end of the illusion, coalescing into the silhouette of a tall hooded figure. The light spilled from the sockets of a skeletal, serene face, flickering flame-blue eyes both eerie and impossibly gentle.\n\nThe dome of light overhead shimmered in slow waves, the gold-silver-bronze fibers humming faintly like a quiet chorus as they stabilized the illusion around them.\n\nAuri’s memory breathed around them.\nIt wasn’t exactly perfect; there were faint signals that it was all just an illusion, like the frays of magic slowly unraveling at the edges. Sol knew he couldn’t keep an illusion of this magnitude up for long, but he would hold out as long as he could for his friend.\n\nSol opened his eyes, a prismatic glow in his irises faded back to his regular gold color; his magic was still wrapped around their forearms in luminous webs, pulsing in time to the memory she’d entrusted to him.\n\nHe looked at her and spoke softly. “Your spark can exist anywhere,” he murmured, his voice threaded with wonder, “even in the places you least expect.”\n\nHis thumb brushed her knuckles again. “Look around you, but look with your heart, not your eyes. I know your spark is here somewhere.”",
    "mentions": [],
    "mention_roles": [],
    "attachments": [],
    "embeds": [],
    "timestamp": "2025-12-10T04:31:36.695000+00:00",
    "edited_timestamp": "2025-12-10T04:31:54.081000+00:00",
    "flags": 0,
    "components": [],
    "id": "1448170264230629397",
    "channel_id": "1442240298800386049",
    "author": {
      "id": "155436835013656576",
      "username": "pyroshadow",
      "avatar": "ed853f9f1777de28c22f287e735ce2b1",
      "discriminator": "0",
      "public_flags": 64,
      "flags": 64,
      "banner": null,
      "accent_color": null,
      "global_name": "Nightingale",
      "avatar_decoration_data": {
        "asset": "a_670b722e56740d11d1e6fe55b8094013",
        "sku_id": "1343751617303805983",
        "expires_at": null
      },
      "collectibles": {
        "nameplate": {
          "sku_id": "1377377712028516443",
          "asset": "nameplates/nameplates_v2/spirit_moon/",
          "label": "COLLECTIBLES_NAMEPLATES_V2_SPIRIT_MOON_A11Y",
          "palette": "violet"
        }
      },
      "display_name_styles": {
        "font_id": 8,
        "effect_id": 2,
        "colors": [
          3163762,
          9709528
        ]
      },
      "banner_color": null,
      "clan": {
        "identity_guild_id": "394252141138804736",
        "identity_enabled": true,
        "tag": "RVYN",
        "badge": "6082c2553b03b47ccaea5203567df3cf"
      },
      "primary_guild": {
        "identity_guild_id": "394252141138804736",
        "identity_enabled": true,
        "tag": "RVYN",
        "badge": "6082c2553b03b47ccaea5203567df3cf"
      }
    },
    "pinned": false,
    "mention_everyone": false,
    "tts": false,
    "position": 18
  },
  {
    "type": 0,
    "content": "Auri didn’t speak at first. \n\nHer breath hitched, quiet but sharp, as the tower shaped itself around them. Her eyes reflected the soft blue firelight, and emotion swelled behind them so quickly she didn’t have time to hide it. Not panic. Not fear. \n\nJust…overwhelmed with wonder, and longing for the home she missed so dearly.\n\nWhen the illusion settled fully, and she recognized the chamber— *his* chamber—- her lips parted in a tiny soundless inhale. Her fingers tightened around Sol’s like she needed something real to anchor her.\n\nHer gaze drifted to the faint silhouette of the man who raised her. Artorius, shrouded in a hooded robe too big for his skeletal figure. For a moment, something fragile flickered through her: a flicker of alarm, a flinch she didn’t quite manage to hide. She hadn’t meant for anyone to see him. Necromancy, after all, was illegal. \n\nBut she didn’t pull away. \n\nInstead, she steadied her breath, gratitude softening every line in her face. She missed him.\n\n“This place…” she murmured, eyes sweeping over the stone, “every part of it made me who I am. It was the first place I felt safe. I never thought anyone outside of my family would ever stand here with me.” \n\nShe looked back to him then, sincerity glowing bright in her amber eyes. “Thank you, Sol. Really. If my spark is anywhere...it’s here.”\n\nAuri closed her eyes, letting the memory settle. Beneath the careful study and theory, she felt a flicker in her chest. A soft, resonant pull. It hummed in her fingers and spine, delicate but undeniable. She pictured the bladesong she’d been chasing: invisible threads of ecto dancing to a rhythm she could finally feel. The song responded to her, flowing naturally, shaped by her own instinct. \n\nHer lips curved in a quiet smile. She opened her eyes, meeting Sol’s gaze, letting the warmth of discovery settle over her. “I…I think I finally hear it,” she whispered. “The song…can you hear it too?”",
    "mentions": [],
    "mention_roles": [],
    "attachments": [],
    "embeds": [],
    "timestamp": "2025-12-14T21:11:36.182000+00:00",
    "edited_timestamp": null,
    "flags": 0,
    "components": [],
    "id": "1449871471781347401",
    "channel_id": "1442240298800386049",
    "author": {
      "id": "697171541208596510",
      "username": "penny5746",
      "avatar": "8d191f8254ab5441078bad8c499e1e00",
      "discriminator": "0",
      "public_flags": 0,
      "flags": 0,
      "banner": null,
      "accent_color": null,
      "global_name": "Penny5746",
      "avatar_decoration_data": null,
      "collectibles": null,
      "display_name_styles": null,
      "banner_color": null,
      "clan": null,
      "primary_guild": null
    },
    "pinned": false,
    "mention_everyone": false,
    "tts": false,
    "position": 19
  },
  {
    "type": 0,
    "content": "Sol watched as Auri took everything in, listening with full attention when she spoke Artorius’s name. Something in his expression softened as she talked about him; it was free of fear and judgment, simply understanding. Sol knew some things didn’t need explanation; he also knew that even though necromancy might be illegal, it didn’t mean good couldn’t come from it.\n\nWhen she looked back at him with gratitude and an unguarded expression, he smiled warmly.\n\n“Anytime,” he said quietly. “Know that you don’t have to thank me for this; my brother would’ve wanted me to use my magic this way.” He smiled at the thought of Lucien.\n\nWhen Auri asked if he could hear what she was, Sol tilted his head slightly and closed his eyes, listening and reaching outward with his magic the way he usually would, but he found only the steady echo of his own magical rhythm.\n\nHe opened his eyes and let out a soft huff; he shook his head, still smiling. \n\n“I can’t hear it,” he admitted. “But I don’t think I’m supposed to.” His smile lingered, fond and certain.\n\n“Sometimes, a song is only meant for one listener.”\n\nAs the words left his mouth, the magic around them began to loosen. The blue fire dimmed first, the glow softening until the silhouette of Artorius faded like smoke. The rain-scented air thinned, the echoes of footsteps dissolving into quiet. Stone softened back into wood beneath them, cold dampness retreating until the familiar warmth of the library floor returned. The dome overhead unraveled in gentle spirals, gold, silver, and bronze threads drifting downward like falling leaves before slipping back into his bracer. The wind died with a sigh. Books and paper fluttered down, and the hush of the library reclaimed the space.\n\nSol glanced around, then back at her, a sheepish grin creeping onto his face.\n\n“Sorry,” he said, rubbing the back of his neck. “I can’t hold something that big for very long.” His voice softened and developed a sincere tone, “But I think you’ve found your tune, right, Prof?” He chuckled to himself, clearly planning to keep that nickname going for her.\n\nHe squeezed her hand once more before letting go, the warmth of the moment lingering even after the magic had gone.",
    "mentions": [],
    "mention_roles": [],
    "attachments": [],
    "embeds": [],
    "timestamp": "2025-12-15T05:07:13.706000+00:00",
    "edited_timestamp": null,
    "flags": 0,
    "components": [],
    "id": "1449991166832541779",
    "channel_id": "1442240298800386049",
    "author": {
      "id": "155436835013656576",
      "username": "pyroshadow",
      "avatar": "ed853f9f1777de28c22f287e735ce2b1",
      "discriminator": "0",
      "public_flags": 64,
      "flags": 64,
      "banner": null,
      "accent_color": null,
      "global_name": "Nightingale",
      "avatar_decoration_data": {
        "asset": "a_670b722e56740d11d1e6fe55b8094013",
        "sku_id": "1343751617303805983",
        "expires_at": null
      },
      "collectibles": {
        "nameplate": {
          "sku_id": "1377377712028516443",
          "asset": "nameplates/nameplates_v2/spirit_moon/",
          "label": "COLLECTIBLES_NAMEPLATES_V2_SPIRIT_MOON_A11Y",
          "palette": "violet"
        }
      },
      "display_name_styles": {
        "font_id": 8,
        "effect_id": 2,
        "colors": [
          3163762,
          9709528
        ]
      },
      "banner_color": null,
      "clan": {
        "identity_guild_id": "394252141138804736",
        "identity_enabled": true,
        "tag": "RVYN",
        "badge": "6082c2553b03b47ccaea5203567df3cf"
      },
      "primary_guild": {
        "identity_guild_id": "394252141138804736",
        "identity_enabled": true,
        "tag": "RVYN",
        "badge": "6082c2553b03b47ccaea5203567df3cf"
      }
    },
    "pinned": false,
    "mention_everyone": false,
    "tts": false,
    "position": 20
  }
]
